linkml_dataops/__init__.py
linkml_dataops/apiroot.py
linkml_dataops/changer/__init__.py
linkml_dataops/changer/changer.py
linkml_dataops/changer/changes.yaml
linkml_dataops/changer/changes_model.py
linkml_dataops/changer/jsonpatch_changer.py
linkml_dataops/changer/object_changer.py
linkml_dataops/diffs/__init__.py
linkml_dataops/diffs/differ.py
linkml_dataops/diffs/yaml_patch.py
linkml_dataops/generators/__init__.py
linkml_dataops/generators/apigenerator.py
linkml_dataops/generators/fastapigenerator.py
linkml_dataops/generators/pyapigenerator.py
linkml_dataops/query/__init__.py
linkml_dataops/query/object_queryengine.py
linkml_dataops/query/query.yaml
linkml_dataops/query/query_model.py
linkml_dataops/query/queryengine.py
linkml_dataops-0.1.0.dist-info/AUTHORS
linkml_dataops-0.1.0.dist-info/METADATA
linkml_dataops-0.1.0.dist-info/WHEEL
linkml_dataops-0.1.0.dist-info/entry_points.txt
linkml_dataops-0.1.0.dist-info/top_level.txt
linkml_dataops-0.1.0.dist-info/RECORD
