Metadata-Version: 1.2
Name: linkml-dataops
Version: 0.1.0
Summary: LinkML Data Operations API
Home-page: http://github.com/linkml/linkml-dataops
Author: Chris Mungall
Author-email: cjmungall@lbl.gov
License: CC0 1.0 Universal
Keywords: linkml,lod,rdf,owl,yaml,model,metamodel
Platform: UNKNOWN
Classifier: Development Status :: 4 - Beta
Classifier: Environment :: Console
Classifier: Intended Audience :: Developers
Classifier: Intended Audience :: Science/Research
Classifier: Intended Audience :: Healthcare Industry
Classifier: License :: CC0 1.0 Universal (CC0 1.0) Public Domain Dedication
Classifier: Programming Language :: Python :: 3 :: Only
Classifier: Programming Language :: Python :: 3.7
Classifier: Programming Language :: Python :: 3.8
Classifier: Programming Language :: Python :: 3.9
Requires-Python: >=3.7
